fastbot/__init__.py
fastbot/bot.py
fastbot/matcher.py
fastbot/message.py
fastbot/plugin.py
fastbot/event/__init__.py
fastbot/event/message.py
fastbot/event/meta.py
fastbot/event/notice.py
fastbot/event/request.py
fastbot_onebot-2025.8.2.dist-info/METADATA
fastbot_onebot-2025.8.2.dist-info/WHEEL
fastbot_onebot-2025.8.2.dist-info/licenses/LICENSE
fastbot_onebot-2025.8.2.dist-info/RECORD
