Metadata-Version: 2.4
Name: fastbot-onebot
Version: 2025.8.2
Summary: A Lightweight BOT Framework.
License: MIT License
License-File: LICENSE
Requires-Python: >=3
Requires-Dist: fastapi
Requires-Dist: uvicorn
Requires-Dist: websockets
